amp_agent/__init__.py
amp_agent/core/__init__.py
amp_agent/core/agent_interface.py
amp_agent/core/agno_adapter.py
amp_agent/core/api.py
amp_agent/core/auth.py
amp_agent/core/config.py
amp_agent/core/db.py
amp_agent/core/jita_helpers.py
amp_agent/core/logging.py
amp_agent/core/models.py
amp_agent/core/process_message_adapter.py
amp_agent/core/server.py
amp_agent/platform/__init__.py
amp_agent/platform/auth_constants.py
amp_agent/platform/auth_manager.py
amp_agent/platform/config_manager.py
amp_agent/platform/platform_manager.py
amp_agent/platform/register_agents.py
amp_agent/semantic/__init__.py
amp_agent/semantic/interest.py
amp_agent/semantic/models.py
amp_agent/subscription/__init__.py
amp_agent/subscription/listen.py
amp_agent/subscription/listen_amp.py
amp_agent/swarm_cell/__init__.py
amp_agent-0.1.4.dist-info/licenses/LICENSE
amp_agent-0.1.4.dist-info/METADATA
amp_agent-0.1.4.dist-info/WHEEL
amp_agent-0.1.4.dist-info/top_level.txt
amp_agent-0.1.4.dist-info/RECORD
