Metadata-Version: 2.4
Name: amp-agent
Version: 0.1.4
Summary: Library for building AMP agents
Author-email: Nexus <nexus@theswarmhub.com>
License-Expression: MIT
Project-URL: Homepage, https://github.com/theswarmhub/amp-agent
Project-URL: Documentation, https://amp-agent.readthedocs.io/
Project-URL: Repository, https://github.com/theswarmhub/amp-agent.git
Project-URL: Issues, https://github.com/theswarmhub/amp-agent/issues
Classifier: Development Status :: 3 - Alpha
Classifier: Intended Audience :: Developers
Classifier: Programming Language :: Python :: 3
Classifier: Programming Language :: Python :: 3.9
Classifier: Programming Language :: Python :: 3.10
Classifier: Programming Language :: Python :: 3.11
Classifier: Topic :: Software Development :: Libraries :: Python Modules
Classifier: Topic :: Internet :: WWW/HTTP :: HTTP Servers
Requires-Python: >=3.9
License-File: LICENSE
Requires-Dist: flask>=2.0.0
Requires-Dist: pydantic>=2.0.0
Requires-Dist: python-jose>=3.3.0
Requires-Dist: httpx>=0.24.0
Requires-Dist: asyncpg>=0.28.0
Requires-Dist: python-dotenv>=1.0.0
Requires-Dist: PyYAML>=6.0
Requires-Dist: requests>=2.31.0
Requires-Dist: colorlog>=6.7.0
Requires-Dist: inquirer>=3.1.3
Requires-Dist: agno>=1.5.5
Requires-Dist: sqlalchemy>=2.0.0
Requires-Dist: psycopg[binary]>=3.1.0
Requires-Dist: psycopg2-binary>=2.9.0
Requires-Dist: numpy>=1.24.0
Requires-Dist: openai>=1.0.0
Requires-Dist: functions_framework>=3.8.3
Provides-Extra: dev
Requires-Dist: pytest>=7.0.0; extra == "dev"
Requires-Dist: pytest-asyncio>=0.21.0; extra == "dev"
Requires-Dist: black>=22.0.0; extra == "dev"
Requires-Dist: isort>=5.0.0; extra == "dev"
Requires-Dist: flake8>=4.0.0; extra == "dev"
Requires-Dist: mypy>=1.0.0; extra == "dev"
Requires-Dist: pytest-cov>=4.0.0; extra == "dev"
Provides-Extra: test
Requires-Dist: pytest>=7.0.0; extra == "test"
Requires-Dist: pytest-asyncio>=0.21.0; extra == "test"
Requires-Dist: pytest-cov>=4.0.0; extra == "test"
Provides-Extra: docs
Requires-Dist: sphinx>=4.0.0; extra == "docs"
Requires-Dist: sphinx-rtd-theme>=1.0.0; extra == "docs"
Requires-Dist: myst-parser>=0.18.0; extra == "docs"
Provides-Extra: ml
Requires-Dist: torch>=2.0.0; extra == "ml"
Requires-Dist: sentence-transformers>=2.2.0; extra == "ml"
Dynamic: license-file
